MANIFEST.in
README.md
setup.cfg
setup.py
opensearch_sibbay.egg-info/PKG-INFO
opensearch_sibbay.egg-info/SOURCES.txt
opensearch_sibbay.egg-info/dependency_links.txt
opensearch_sibbay.egg-info/requires.txt
opensearch_sibbay.egg-info/top_level.txt
opensearchsdk/__init__.py
opensearchsdk/client.py
opensearchsdk/demo.py
opensearchsdk/apiclient/__init__.py
opensearchsdk/apiclient/api_base.py
opensearchsdk/apiclient/exceptions.py
opensearchsdk/tests/__init__.py
opensearchsdk/tests/base.py
opensearchsdk/tests/test_client.py
opensearchsdk/tests/apiclient/__init__.py
opensearchsdk/tests/apiclient/test_base.py
opensearchsdk/tests/utils/__init__.py
opensearchsdk/tests/utils/test_prepare_url.py
opensearchsdk/tests/v2/__init__.py
opensearchsdk/tests/v2/test_app.py
opensearchsdk/tests/v2/test_data.py
opensearchsdk/tests/v2/test_index.py
opensearchsdk/tests/v2/test_log.py
opensearchsdk/tests/v2/test_search.py
opensearchsdk/tests/v2/test_suggest.py
opensearchsdk/utils/__init__.py
opensearchsdk/utils/prepare_url.py
opensearchsdk/v2/__init__.py
opensearchsdk/v2/app.py
opensearchsdk/v2/data.py
opensearchsdk/v2/index.py
opensearchsdk/v2/log.py
opensearchsdk/v2/quota.py
opensearchsdk/v2/search.py
opensearchsdk/v2/suggest.py