Metadata-Version: 1.1
Name: opensearch-sibbay
Version: 2.1.1
Summary: Python SDK for OpenSearch of Ali Cloud
Home-page: https://github.com/sibbay-ai/opensearch
Author: Bin Chen
Author-email: sinchb128@gmail.com
License: Apache License Version 2.0
Keywords: OpenSearch SDK,Aliyun for Sibbay
Platform: any
Classifier: Operating System :: MacOS
Classifier: Operating System :: Microsoft :: Windows
Classifier: Operating System :: POSIX :: Linux
Classifier: Programming Language :: Python
Classifier: Programming Language :: Python :: 2.7
Classifier: Programming Language :: Python :: 3.5
